pydbsmgr/__init__.py
pydbsmgr/fast_upload.py
pydbsmgr/health.py
pydbsmgr/lightest.py
pydbsmgr/logs.py
pydbsmgr/main.py
pydbsmgr/utils/__init__.py
pydbsmgr/utils/azure_sdk.py
pydbsmgr/utils/config.py
pydbsmgr/utils/tools.py
pydbsmgr-1.0.2.dist-info/licenses/LICENSE
test/__init__.py
test/conftest.py
test/test_functions.py
pydbsmgr-1.0.2.dist-info/METADATA
pydbsmgr-1.0.2.dist-info/WHEEL
pydbsmgr-1.0.2.dist-info/top_level.txt
pydbsmgr-1.0.2.dist-info/RECORD
