Metadata-Version: 2.4
Name: pydbsmgr
Version: 1.0.2
Summary: Python package for database control and DataFrame processing
Home-page: https://github.com/jzsmoreno/pydbsmgr
Author: J. A. Moreno-Guerra
Author-email: jzs.gm27@gmail.com
Maintainer: David Pedroza
Maintainer-email: david.pedroza.segoviano@gmail.com
License: MIT
Project-URL: Bug Tracker, https://github.com/jzsmoreno/pydbsmgr
Classifier: Programming Language :: Python :: 3
Classifier: License :: OSI Approved :: MIT License
Classifier: Operating System :: OS Independent
Requires-Python: >=3.10
License-File: LICENSE
Requires-Dist: numpy<2.0.0
Requires-Dist: pandas
Requires-Dist: polars
Requires-Dist: missingno
Requires-Dist: pyodbc
Requires-Dist: ipython
Requires-Dist: SQLAlchemy
Requires-Dist: pyyaml
Requires-Dist: azure-storage-blob==12.16.0
Requires-Dist: python-dotenv==1.0.0
Requires-Dist: openpyxl==3.1.2
Requires-Dist: pyarrow
Requires-Dist: fastparquet
Requires-Dist: loguru
Requires-Dist: psutil
Requires-Dist: Unidecode
Dynamic: author
Dynamic: author-email
Dynamic: classifier
Dynamic: description
Dynamic: description-content-type
Dynamic: home-page
Dynamic: license
Dynamic: license-file
Dynamic: maintainer
Dynamic: maintainer-email
Dynamic: project-url
Dynamic: requires-dist
Dynamic: requires-python
Dynamic: summary
